sonicpure/__init__.py
sonicpure/engines.py
sonicpure/pipeline.py
sonicpure/processors.py
sonicpure-0.1.1.dist-info/licenses/LICENSE
sonicpure-0.1.1.dist-info/METADATA
sonicpure-0.1.1.dist-info/WHEEL
sonicpure-0.1.1.dist-info/entry_points.txt
sonicpure-0.1.1.dist-info/top_level.txt
sonicpure-0.1.1.dist-info/RECORD
