Metadata-Version: 2.4
Name: sonicpure
Version: 0.1.1
Summary: Audio noise reduction and enhancement library with multiple engines
Home-page: https://github.com/mytsx/sonicpure
Author: Mehmet Yerli
Author-email: Mehmet Yerli <iletisim@mehmetyerli.com.tr>
License: MIT
Project-URL: Homepage, https://github.com/mytsx/sonicpure
Project-URL: Repository, https://github.com/mytsx/sonicpure
Project-URL: Bug Tracker, https://github.com/mytsx/sonicpure/issues
Keywords: audio,noise-reduction,speech-enhancement,denoising,rnnoise,speechbrain,audio-processing
Classifier: Development Status :: 4 - Beta
Classifier: Intended Audience :: Developers
Classifier: Topic :: Multimedia :: Sound/Audio :: Analysis
Classifier: Topic :: Multimedia :: Sound/Audio :: Editors
Classifier: License :: OSI Approved :: MIT License
Classifier: Programming Language :: Python :: 3
Classifier: Programming Language :: Python :: 3.8
Classifier: Programming Language :: Python :: 3.9
Classifier: Programming Language :: Python :: 3.10
Classifier: Programming Language :: Python :: 3.11
Classifier: Programming Language :: Python :: 3.12
Classifier: Programming Language :: Python :: 3.13
Requires-Python: >=3.8
License-File: LICENSE
Requires-Dist: numpy>=1.20.0
Requires-Dist: scipy>=1.7.0
Requires-Dist: soundfile>=0.11.0
Requires-Dist: noisereduce>=3.0.0
Requires-Dist: pyrnnoise>=0.4.0
Requires-Dist: speechbrain>=1.0.0
Requires-Dist: torch>=2.0.0
Requires-Dist: torchaudio>=2.0.0
Requires-Dist: tqdm>=4.60.0
Provides-Extra: dev
Requires-Dist: pytest>=7.0.0; extra == "dev"
Requires-Dist: pytest-cov>=4.0.0; extra == "dev"
Requires-Dist: black>=23.0.0; extra == "dev"
Requires-Dist: flake8>=6.0.0; extra == "dev"
Dynamic: author
Dynamic: home-page
Dynamic: license-file
Dynamic: requires-python
